MANIFEST.in
README.md
setup.py
yql/__init__.py
yql/_builder.py
yql.egg-info/PKG-INFO
yql.egg-info/SOURCES.txt
yql.egg-info/dependency_links.txt
yql.egg-info/requires.txt
yql.egg-info/top_level.txt
yql/api/__init__.py
yql/api/_api_mapper.py
yql/api/_api_request.py
yql/api/_api_response.py