Metadata-Version: 1.1
Name: yql
Version: 1.0.1
Summary: python interface for yql
Home-page: https://github.com/plasmashadow/yql.git
Author: plasmashadow
Author-email: plasmashadowx@gmail.com
License: MIT
Platform: UNKNOWN
Classifier: Programming Language :: Python
Classifier: License :: OSI Approved :: GNU General Public License (GPL)
Classifier: Operating System :: OS Independent
Classifier: Development Status :: 1 - Planning
Classifier: Environment :: Console
Classifier: Intended Audience :: Science/Research
